token_tango/__init__.py
token_tango/config.py
token_tango/excpetions.py
token_tango/key_manager.py
token_tango/key_rotation_consumer.py
token_tango/key_rotation_event.py
token_tango/middleware.py
token_tango/singleton_meta.py
token_tango/version.py
token_tango-0.0.1.dist-info/METADATA
token_tango-0.0.1.dist-info/WHEEL
token_tango-0.0.1.dist-info/entry_points.txt
token_tango-0.0.1.dist-info/top_level.txt
token_tango-0.0.1.dist-info/RECORD
